{"name":"build-javascript","namedChunkGroups":{"app":{"name":"app","assets":[{"name":"webpack-runtime-69bee3da440b67415369.js","size":3879},{"name":"framework-63ef48a3d5ef8a8aaad8.js","size":140297},{"name":"styles.685a165e917b79a1e250.css","size":22297},{"name":"app-31e4f6016d6d23a6cd38.js","size":73062}],"filteredAssets":0,"assetsSize":239535,"filteredAuxiliaryAssets":3,"auxiliaryAssetsSize":643558},"component---src-pages-guides-js":{"name":"component---src-pages-guides-js","assets":[{"name":"component---src-pages-guides-js-f9e8fe3a139951d82981.js","size":17285}],"filteredAssets":0,"assetsSize":17285,"filteredAuxiliaryAssets":1,"auxiliaryAssetsSize":26382},"component---src-pages-index-js":{"name":"component---src-pages-index-js","assets":[{"name":"component---src-pages-index-js-943116bf3938dc7496d8.js","size":24886}],"filteredAssets":0,"assetsSize":24886,"filteredAuxiliaryAssets":1,"auxiliaryAssetsSize":43386},"component---src-pages-projects-js":{"name":"component---src-pages-projects-js","assets":[{"name":"component---src-pages-projects-js-b968ea07d5ff82520e82.js","size":11569}],"filteredAssets":0,"assetsSize":11569,"filteredAuxiliaryAssets":1,"auxiliaryAssetsSize":21047}},"assetsByChunkName":{"app":["webpack-runtime-69bee3da440b67415369.js","framework-63ef48a3d5ef8a8aaad8.js","styles.685a165e917b79a1e250.css","app-31e4f6016d6d23a6cd38.js"],"component---src-pages-guides-js":["component---src-pages-guides-js-f9e8fe3a139951d82981.js"],"component---src-pages-index-js":["component---src-pages-index-js-943116bf3938dc7496d8.js"],"component---src-pages-projects-js":["component---src-pages-projects-js-b968ea07d5ff82520e82.js"]},"childAssetsByChunkName":{}}